the_well_maintained_test/__init__.py
the_well_maintained_test/_version.py
the_well_maintained_test/cli.py
the_well_maintained_test/console.py
the_well_maintained_test/errors.py
the_well_maintained_test/headers.py
the_well_maintained_test/helpers.py
the_well_maintained_test/styles.py
the_well_maintained_test/utils.py
the_well_maintained_test/data/__init__.py
the_well_maintained_test/data/questions.json
the_well_maintained_test/data/questions.toml
the_well_maintained_test/data/urls.toml
the_well_maintained_test-0.12.0.dist-info/METADATA
the_well_maintained_test-0.12.0.dist-info/WHEEL
the_well_maintained_test-0.12.0.dist-info/entry_points.txt
the_well_maintained_test-0.12.0.dist-info/licenses/LICENSE
the_well_maintained_test-0.12.0.dist-info/RECORD
