Metadata-Version: 2.4
Name: the-well-maintained-test
Version: 0.12.0
Summary: Programatically tries to answer the 12 questions from Adam Johnson's blog post https://adamj.eu/tech/2021/11/04/the-well-maintained-test/
Project-URL: Issues, https://github.com/ryancheley/the-well-maintained-test/issues
Project-URL: CI, https://github.com/ryancheley/the-well-maintained-test/actions
Project-URL: Changelog, https://github.com/ryancheley/the-well-maintained-test/releases
Author: Ryan Cheley
License: Apache-2.0
License-File: LICENSE
Classifier: Development Status :: 4 - Beta
Requires-Python: >=3.9
Requires-Dist: click
Requires-Dist: importlib-resources
Requires-Dist: requests
Requires-Dist: rich
Requires-Dist: toml
Provides-Extra: dev
Requires-Dist: build>=1.2.2.post1; extra == 'dev'
Requires-Dist: cogapp; extra == 'dev'
Requires-Dist: packaging; extra == 'dev'
Requires-Dist: pre-commit>=4.2.0; extra == 'dev'
Requires-Dist: ruff; extra == 'dev'
Requires-Dist: twine>=6.1.0; extra == 'dev'
Provides-Extra: docs
Requires-Dist: markdown-include; extra == 'docs'
Requires-Dist: mkdocs; extra == 'docs'
Requires-Dist: mkdocstrings[python]; extra == 'docs'
Provides-Extra: test
Requires-Dist: coverage; extra == 'test'
Requires-Dist: mypy; extra == 'test'
Requires-Dist: pytest; extra == 'test'
